setup.cfg
setup.py
scnn/__init__.py
scnn/baseline_edge_experiment.py
scnn/baseline_graph_experiment.py
scnn/baseline_node_experiment.py
scnn/data.py
scnn/edge_experiment.py
scnn/edge_scnn.py
scnn/graph_experiment.py
scnn/graph_scnn.py
scnn/kernel.py
scnn/node_experiment.py
scnn/node_proportion_experiment.py
scnn/scnn.py
scnn/util.py
scnn.egg-info/PKG-INFO
scnn.egg-info/SOURCES.txt
scnn.egg-info/dependency_links.txt
scnn.egg-info/requires.txt
scnn.egg-info/top_level.txt
scnn/dgk/__init__.py
scnn/dgk/deep_kernel.py