Metadata-Version: 1.1
Name: scnn
Version: 1.3.1
Summary: Search-Convolutional Neural Networks
Home-page: https://github.com/jcatw/scnn
Author: James Atwood
Author-email: james.c.atwood@gmail.com
License: MIT
Keywords: search convolutional neural networks machine learning
Platform: UNKNOWN
Classifier: Development Status :: 3 - Alpha
Classifier: Intended Audience :: Science/Research
Classifier: Topic :: Scientific/Engineering :: Artificial Intelligence
Classifier: License :: OSI Approved :: MIT License
Classifier: Programming Language :: Python :: 2
Classifier: Programming Language :: Python :: 2.6
Classifier: Programming Language :: Python :: 2.7
